{
  "query_id": "query_018",
  "session_id": "25-index-sentwindow-markdown-Overnight-30q-v1-20260315-125128",
  "timestamp": "2026-03-15T12:54:49.328153",
  "query": {
    "original": "Does Sneak Attack require the rogue to be hidden?",
    "used": "Does Sneak Attack require the rogue to be hidden?"
  },
  "retrieved_nodes": [
    {
      "rank": 1,
      "score": 0.016666666666666666,
      "category": "Classes",
      "topic": "Rogue",
      "file": "E:\\Programms\\JetBrains\\_Projects\\Python\\SeminarRAG\\src\\..\\data\\DND.SRD.Wiki-0.5.2\\Classes\\Rogue.md",
      "preview": "### Sneak Attack\n\nBeginning at 1st level, you know how to strike subtly and exploit a foe's distraction. "
    },
    {
      "rank": 2,
      "score": 0.01639344262295082,
      "category": "Classes",
      "topic": "Rogue",
      "file": "E:\\Programms\\JetBrains\\_Projects\\Python\\SeminarRAG\\src\\..\\data\\DND.SRD.Wiki-0.5.2\\Classes\\Rogue.md",
      "preview": "#### Supreme Sneak\n\nStarting at 9th level, you have advantage on a Dexterity (Stealth) check if you move no more than half your speed on the same turn.\n\n"
    },
    {
      "rank": 3,
      "score": 0.016129032258064516,
      "category": "Classes",
      "topic": "Rogue",
      "file": "E:\\Programms\\JetBrains\\_Projects\\Python\\SeminarRAG\\src\\..\\data\\DND.SRD.Wiki-0.5.2\\Classes\\Rogue.md",
      "preview": "You don't need advantage on the attack roll if another enemy of the target is within 5 feet of it, that enemy isn't incapacitated, and you don't have disadvantage on the attack roll.\n\n"
    },
    {
      "rank": 4,
      "score": 0.015873015873015872,
      "category": "Classes",
      "topic": "Rogue",
      "file": "E:\\Programms\\JetBrains\\_Projects\\Python\\SeminarRAG\\src\\..\\data\\DND.SRD.Wiki-0.5.2\\Classes\\Rogue.md",
      "preview": "#### Hit Points\n\n**Hit Dice:** 1d8 per rogue level\n\n**Hit Points at 1st Level:** 8 + your Constitution modifier\n\n**Hit Points at Higher Levels:** 1d8 (or 5) + your Constitution modifier per rogue leve"
    },
    {
      "rank": 5,
      "score": 0.015625,
      "category": "Classes",
      "topic": "Rogue",
      "file": "E:\\Programms\\JetBrains\\_Projects\\Python\\SeminarRAG\\src\\..\\data\\DND.SRD.Wiki-0.5.2\\Classes\\Rogue.md",
      "preview": "No attack roll has advantage against you while you aren't incapacitated.\n\n"
    },
    {
      "rank": 6,
      "score": 0.015384615384615385,
      "category": "Classes",
      "topic": "Rogue",
      "file": "E:\\Programms\\JetBrains\\_Projects\\Python\\SeminarRAG\\src\\..\\data\\DND.SRD.Wiki-0.5.2\\Classes\\Rogue.md",
      "preview": "### Elusive\n\nBeginning at 18th level, you are so evasive that attackers rarely gain the upper hand against you. "
    },
    {
      "rank": 7,
      "score": 0.015151515151515152,
      "category": "Gameplay",
      "topic": "Combat",
      "file": "E:\\Programms\\JetBrains\\_Projects\\Python\\SeminarRAG\\src\\..\\data\\DND.SRD.Wiki-0.5.2\\Gameplay\\Combat.md",
      "preview": "If the attack involves other damage dice, such as from the rogue's Sneak Attack feature, you roll those dice twice as well.\n\n"
    },
    {
      "rank": 8,
      "score": 0.014925373134328358,
      "category": "Classes",
      "topic": "Rogue",
      "file": "E:\\Programms\\JetBrains\\_Projects\\Python\\SeminarRAG\\src\\..\\data\\DND.SRD.Wiki-0.5.2\\Classes\\Rogue.md",
      "preview": "### Thieves' Cant\n\nDuring your rogue training you learned thieves' cant, a secret mix of dialect, jargon, and code that allows you to hide messages in seemingly normal conversation. "
    },
    {
      "rank": 9,
      "score": 0.014705882352941176,
      "category": "Gameplay",
      "topic": "Combat",
      "file": "E:\\Programms\\JetBrains\\_Projects\\Python\\SeminarRAG\\src\\..\\data\\DND.SRD.Wiki-0.5.2\\Gameplay\\Combat.md",
      "preview": "## Unseen Attackers and Targets\n\nCombatants often try to escape their foes' notice by hiding, casting the invisibility spell, or lurking in darkness.\n\n"
    },
    {
      "rank": 10,
      "score": 0.014492753623188406,
      "category": "Classes",
      "topic": "Rogue",
      "file": "E:\\Programms\\JetBrains\\_Projects\\Python\\SeminarRAG\\src\\..\\data\\DND.SRD.Wiki-0.5.2\\Classes\\Rogue.md",
      "preview": "### Blindsense\n\nStarting at 14th level, if you are able to hear, you are aware of the location of any hidden or invisible creature within 10 feet of you.\n\n"
    }
  ],
  "tokens": {
    "rag_prompt": 1937,
    "rag_completion": 2250,
    "meta_prompt": 0,
    "meta_completion": 0,
    "total_calls": 1,
    "total": 4187
  },
  "costs": {
    "rag": 0.00064057,
    "meta": 0.0,
    "embed": 0.0,
    "total": 0.00064057
  },
  "timings": {
    "rag_s": 0.0,
    "query_s": 6.77,
    "total_s": 14.27
  },
  "answer": " The context does not explicitly state that the rogue must be hidden to perform a Sneak Attack. However, the name of the ability implies that some level of stealth or subterfuge is involved. The rules do not provide enough context to determine if being hidden is a requirement or just a common method for achieving a Sneak Attack. Therefore, I cannot definitively answer this question with the provided rules alone.",
  "refused": false,
  "confidence": {
    "passed": false,
    "best_score": 0.016666666666666666
  },
  "evaluation": {
    "faithfulness": {
      "score": 0.0,
      "passing": false,
      "feedback": "NO"
    },
    "relevancy": {
      "score": 0.0,
      "passing": false,
      "feedback": "NO"
    },
    "correctness": {
      "score": 2.0,
      "passing": false,
      "feedback": "The generated answer is relevant to the user query but contains inaccuracies and lacks clarity. It correctly states that being hidden is not a requirement for Sneak Attack, but it introduces unnecessary ambiguity by suggesting that the rules do not provide enough context, which is misleading. The reference answer clearly states the conditions for Sneak Attack, which the generated answer fails to do."
    },
    "context_relevancy": {
      "score": 0.25,
      "passing": null,
      "feedback": "1. **Does the retrieved context match the subject matter of the user's query?**\n   - The retrieved context discusses the Sneak Attack feature of the rogue class in D&D 5e, including details about how it works and the conditions under which it can be used. However, it does not explicitly state whether the rogue needs to be hidden to use Sneak Attack. The relevant part of the rules is that a rogue does not need advantage on the attack roll if another enemy of the target is within 5 feet of it, but it does not clarify the requirement of being hidden. Therefore, while the context is related to the query, it does not directly answer the question about the necessity of being hidden for Sneak Attack. \n   - **Score: 1/2**\n\n2. **Can the retrieved context be used exclusively to provide a full answer to the user's query?**\n   - The context does not provide a complete answer to the user's query regarding whether being hidden is a requirement for Sneak Attack. It lacks specific information about the need for stealth or hiding, which is crucial to fully address the question. Thus, while it contains relevant information about the Sneak Attack feature, it cannot be used exclusively to answer the query.\n   - **Score: 0/2**\n\n**Final Feedback:**\nThe retrieved context provides some relevant information about the Sneak Attack feature but fails to directly address the user's question about the requirement of being hidden. It lacks clarity on this specific point, which is essential for a complete answer. Therefore, the context is partially relevant but insufficient for a full response.\n\n[RESULT] 1.0"
    }
  }
}