{
  "query_id": "query_029",
  "session_id": "35-retrieval-topk15-Overnight-30q-v1-20260315-135829",
  "timestamp": "2026-03-15T14:05:47.843162",
  "query": {
    "original": "Does a Barbarian lose their Rage bonus damage if they cast a spell while raging?",
    "used": "Does a Barbarian lose their Rage bonus damage if they cast a spell while raging?"
  },
  "retrieved_nodes": [
    {
      "rank": 1,
      "score": 0.016666666666666666,
      "category": "Classes",
      "topic": "Barbarian",
      "file": "E:\\Programms\\JetBrains\\_Projects\\Python\\SeminarRAG\\src\\..\\data\\DND.SRD.Wiki-0.5.2\\Classes\\Barbarian.md",
      "preview": "### Rage\n\nIn battle, you fight with primal ferocity. On your turn, you can enter a rage as a bonus action.\n\nWhile raging, you gain the following benefits if you aren't wearing heavy armor:\n\n- You have"
    },
    {
      "rank": 2,
      "score": 0.01639344262295082,
      "category": "Classes",
      "topic": "Barbarian",
      "file": "E:\\Programms\\JetBrains\\_Projects\\Python\\SeminarRAG\\src\\..\\data\\DND.SRD.Wiki-0.5.2\\Classes\\Barbarian.md",
      "preview": "### Relentless Rage\n\nStarting at 11th level, your rage can keep you fighting despite grievous wounds. If you drop to 0 hit points while you're raging and don't die outright, you can make a DC 10 Const"
    },
    {
      "rank": 3,
      "score": 0.016129032258064516,
      "category": "Classes",
      "topic": "Barbarian",
      "file": "E:\\Programms\\JetBrains\\_Projects\\Python\\SeminarRAG\\src\\..\\data\\DND.SRD.Wiki-0.5.2\\Classes\\Barbarian.md",
      "preview": "#### Mindless Rage\n\nBeginning at 6th level, you can't be charmed or frightened while raging. If you are charmed or frightened when you enter your rage, the effect is suspended for the duration of the "
    },
    {
      "rank": 4,
      "score": 0.015873015873015872,
      "category": "Classes",
      "topic": "Barbarian",
      "file": "E:\\Programms\\JetBrains\\_Projects\\Python\\SeminarRAG\\src\\..\\data\\DND.SRD.Wiki-0.5.2\\Classes\\Barbarian.md",
      "preview": "#### Frenzy\n\nStarting when you choose this path at 3rd level, you can go into a frenzy when you rage. If you do so, for the duration of your rage you can make a single melee weapon attack as a bonus a"
    },
    {
      "rank": 5,
      "score": 0.015625,
      "category": "Classes",
      "topic": "Barbarian",
      "file": "E:\\Programms\\JetBrains\\_Projects\\Python\\SeminarRAG\\src\\..\\data\\DND.SRD.Wiki-0.5.2\\Classes\\Barbarian.md",
      "preview": "### Feral Instinct\n\nBy 7th level, your instincts are so honed that you have advantage on initiative rolls.\n\nAdditionally, if you are surprised at the beginning of combat and aren't incapacitated, you "
    },
    {
      "rank": 6,
      "score": 0.015384615384615385,
      "category": "Classes",
      "topic": "Barbarian",
      "file": "E:\\Programms\\JetBrains\\_Projects\\Python\\SeminarRAG\\src\\..\\data\\DND.SRD.Wiki-0.5.2\\Classes\\Barbarian.md",
      "preview": "### Persistent Rage\n\nBeginning at 15th level, your rage is so fierce that it ends early only if you fall unconscious or if you choose to end it."
    },
    {
      "rank": 7,
      "score": 0.015151515151515152,
      "category": "Classes",
      "topic": "Barbarian",
      "file": "E:\\Programms\\JetBrains\\_Projects\\Python\\SeminarRAG\\src\\..\\data\\DND.SRD.Wiki-0.5.2\\Classes\\Barbarian.md",
      "preview": "### Danger Sense\n\nAt 2nd level, you gain an uncanny sense of when things nearby aren't as they should be, giving you an edge when you dodge away from danger.\n\nYou have advantage on Dexterity saving th"
    },
    {
      "rank": 8,
      "score": 0.014925373134328358,
      "category": "Classes",
      "topic": "Barbarian",
      "file": "E:\\Programms\\JetBrains\\_Projects\\Python\\SeminarRAG\\src\\..\\data\\DND.SRD.Wiki-0.5.2\\Classes\\Barbarian.md",
      "preview": "### Reckless Attack\n\nStarting at 2nd level, you can throw aside all concern for defense to attack with fierce desperation. When you make your first attack on your turn, you can decide to attack reckle"
    },
    {
      "rank": 9,
      "score": 0.014705882352941176,
      "category": "Gamemastering",
      "topic": "Madness",
      "file": "E:\\Programms\\JetBrains\\_Projects\\Python\\SeminarRAG\\src\\..\\data\\DND.SRD.Wiki-0.5.2\\Gamemastering\\Madness.md",
      "preview": "### Curing Madness\n\nA *calm emotions* spell can suppress the effects of madness, while a *lesser restoration* spell can rid a character of a short-term or long-term madness. Depending on the source of"
    },
    {
      "rank": 10,
      "score": 0.014492753623188406,
      "category": "Classes",
      "topic": "Wizard",
      "file": "E:\\Programms\\JetBrains\\_Projects\\Python\\SeminarRAG\\src\\..\\data\\DND.SRD.Wiki-0.5.2\\Classes\\Wizard.md",
      "preview": "#### Potent Cantrip\n\nStarting at 6th level, your damaging cantrips affect even creatures that avoid the brunt of the effect. When a creature succeeds on a saving throw against your cantrip, the creatu"
    },
    {
      "rank": 11,
      "score": 0.014285714285714285,
      "category": "Spells",
      "topic": "Calm Emotions",
      "file": "E:\\Programms\\JetBrains\\_Projects\\Python\\SeminarRAG\\src\\..\\data\\DND.SRD.Wiki-0.5.2\\Spells\\Calm Emotions.md",
      "preview": "### Calm Emotions\n\n*2nd-level enchantment*\n\n**Casting Time:** 1 action\n\n**Range:** 60 feet\n\n**Components:** V, S\n\n**Duration:** Concentration, up to 1 minute\n\nYou attempt to suppress strong emotions i"
    },
    {
      "rank": 12,
      "score": 0.014084507042253521,
      "category": "Spells",
      "topic": "Vicious Mockery",
      "file": "E:\\Programms\\JetBrains\\_Projects\\Python\\SeminarRAG\\src\\..\\data\\DND.SRD.Wiki-0.5.2\\Spells\\Vicious Mockery.md",
      "preview": "### Vicious Mockery\n\n*Enchantment cantrip*\n\n**Casting Time:** 1 action\n\n**Range:** 60 feet\n\n**Components:** V\n\n**Duration:** Instantaneous\n\nYou unleash a string of insults laced with subtle enchantmen"
    },
    {
      "rank": 13,
      "score": 0.013888888888888888,
      "category": "Spells",
      "topic": "Heroism",
      "file": "E:\\Programms\\JetBrains\\_Projects\\Python\\SeminarRAG\\src\\..\\data\\DND.SRD.Wiki-0.5.2\\Spells\\Heroism.md",
      "preview": "### Heroism\n\n*1st-level enchantment*\n\n**Casting Time:** 1 action\n\n**Range:** Touch\n\n**Components:** V, S\n\n**Duration:** Concentration, up to 1 minute\n\nA willing creature you touch is imbued with brave"
    },
    {
      "rank": 14,
      "score": 0.0136986301369863,
      "category": "Classes",
      "topic": "Barbarian",
      "file": "E:\\Programms\\JetBrains\\_Projects\\Python\\SeminarRAG\\src\\..\\data\\DND.SRD.Wiki-0.5.2\\Classes\\Barbarian.md",
      "preview": "#### Intimidating Presence\n\nBeginning at 10th level, you can use your action to frighten someone with your menacing presence. When you do so, choose one creature that you can see within 30 feet of you"
    },
    {
      "rank": 15,
      "score": 0.013513513513513514,
      "category": "Classes",
      "topic": "Barbarian",
      "file": "E:\\Programms\\JetBrains\\_Projects\\Python\\SeminarRAG\\src\\..\\data\\DND.SRD.Wiki-0.5.2\\Classes\\Barbarian.md",
      "preview": "### Primal Path\n\nAt 3rd level, you choose a path that shapes the nature of your rage. Choose the Path of the Berserker or the Path of the Totem Warrior, both detailed at the end of the class descripti"
    }
  ],
  "tokens": {
    "rag_prompt": 2997,
    "rag_completion": 3244,
    "meta_prompt": 0,
    "meta_completion": 0,
    "total_calls": 1,
    "total": 6241
  },
  "costs": {
    "rag": 0.00094603,
    "meta": 0.0,
    "embed": 0.0,
    "total": 0.00094603
  },
  "timings": {
    "rag_s": 0.0,
    "query_s": 5.42,
    "total_s": 13.21
  },
  "answer": " I cannot find this in the provided rules whether a Barbarian loses their Rage bonus damage if they cast a spell while raging. The context only mentions the benefits of Rage and the Primal Path feature, but it does not specify any restrictions related to casting spells while raging.",
  "refused": false,
  "confidence": {
    "passed": false,
    "best_score": 0.016666666666666666
  },
  "evaluation": {
    "faithfulness": {
      "score": 0.0,
      "passing": false,
      "feedback": "NO"
    },
    "relevancy": {
      "score": 0.0,
      "passing": false,
      "feedback": "NO"
    },
    "correctness": {
      "score": 2.0,
      "passing": false,
      "feedback": "The generated answer is relevant to the user query but contains inaccuracies regarding the rules. It incorrectly states that the rules do not specify restrictions on spellcasting while raging, when in fact, the rules clearly state that a Barbarian cannot cast spells while raging."
    },
    "context_relevancy": {
      "score": 1.0,
      "passing": null,
      "feedback": "1. **Does the retrieved context match the subject matter of the user's query?**  \n   Yes, the retrieved context directly addresses the subject matter of the user's query regarding a Barbarian's Rage and its interaction with spellcasting. The context clearly states that if a Barbarian is able to cast spells, they cannot do so while raging. This implies that if a Barbarian were to cast a spell, they would not be able to maintain their Rage, and thus would lose the benefits associated with it, including the bonus damage from Rage.\n\n   **Score: 2 points**\n\n2. **Can the retrieved context be used exclusively to provide a full answer to the user's query?**  \n   Yes, the context provides a complete answer to the user's query. It explains that a Barbarian cannot cast spells while raging, which directly leads to the conclusion that if they were to cast a spell, they would lose their Rage and the associated bonus damage. The information is sufficient to fully address the question without needing additional context or information.\n\n   **Score: 2 points**\n\n**Final Result:** [RESULT] 4.0"
    }
  }
}