{
  "query_id": "query_030",
  "session_id": "71-prompt-soft-Overnight-30q-v1-20260315-150804",
  "timestamp": "2026-03-15T15:14:19.198225",
  "query": {
    "original": "Can you cast a spell and also make a weapon attack in the same turn without any special features?",
    "used": "Can you cast a spell and also make a weapon attack in the same turn without any special features?"
  },
  "retrieved_nodes": [
    {
      "rank": 1,
      "score": 0.016666666666666666,
      "category": "Spells",
      "topic": "# Spellcasting",
      "file": "E:\\Programms\\JetBrains\\_Projects\\Python\\SeminarRAG\\src\\..\\data\\DND.SRD.Wiki-0.5.2\\Spells\\# Spellcasting.md",
      "preview": "### Bonus Action\n\nA spell cast with a bonus action is especially swift. You must use a bonus action on your turn to cast the spell, provided that you haven't already taken a bonus action this turn. Yo"
    },
    {
      "rank": 2,
      "score": 0.01639344262295082,
      "category": "Gameplay",
      "topic": "Combat",
      "file": "E:\\Programms\\JetBrains\\_Projects\\Python\\SeminarRAG\\src\\..\\data\\DND.SRD.Wiki-0.5.2\\Gameplay\\Combat.md",
      "preview": "# Making an Attack\n\nWhether you're striking with a melee weapon, firing a weapon at range, or making an attack roll as part of a spell, an attack has a simple structure.\n\n- **Choose a target**. Pick a"
    },
    {
      "rank": 3,
      "score": 0.016129032258064516,
      "category": "Monsters",
      "topic": "# Monster Statistics",
      "file": "E:\\Programms\\JetBrains\\_Projects\\Python\\SeminarRAG\\src\\..\\data\\DND.SRD.Wiki-0.5.2\\Monsters\\# Monster Statistics.md",
      "preview": "### Innate Spellcasting\n\nA monster with the innate ability to cast spells has the Innate Spellcasting special trait. Unless noted otherwise, an innate spell of 1st level or higher is always cast at it"
    },
    {
      "rank": 4,
      "score": 0.015873015873015872,
      "category": "Gameplay",
      "topic": "Combat",
      "file": "E:\\Programms\\JetBrains\\_Projects\\Python\\SeminarRAG\\src\\..\\data\\DND.SRD.Wiki-0.5.2\\Gameplay\\Combat.md",
      "preview": "### Two-Weapon Fighting\n\nWhen you take the Attack action and attack with a light melee weapon that you're holding in one hand, you can use a bonus action to attack with a different light melee weapon "
    },
    {
      "rank": 5,
      "score": 0.015625,
      "category": "Gameplay",
      "topic": "Combat",
      "file": "E:\\Programms\\JetBrains\\_Projects\\Python\\SeminarRAG\\src\\..\\data\\DND.SRD.Wiki-0.5.2\\Gameplay\\Combat.md",
      "preview": "### Damage Rolls\n\nEach weapon, spell, and harmful monster ability specifies the damage it deals. You roll the damage die or dice, add any modifiers, and apply the damage to your target. Magic weapons,"
    },
    {
      "rank": 6,
      "score": 0.015384615384615385,
      "category": "Classes",
      "topic": "Warlock",
      "file": "E:\\Programms\\JetBrains\\_Projects\\Python\\SeminarRAG\\src\\..\\data\\DND.SRD.Wiki-0.5.2\\Classes\\Warlock.md",
      "preview": "#### Pact of the Chain\n\nYou learn the *find familiar* spell and can cast it as a ritual. The spell doesn't count against your number of spells known.\n\nWhen you cast the spell, you can choose one of th"
    },
    {
      "rank": 7,
      "score": 0.015151515151515152,
      "category": "Gameplay",
      "topic": "Combat",
      "file": "E:\\Programms\\JetBrains\\_Projects\\Python\\SeminarRAG\\src\\..\\data\\DND.SRD.Wiki-0.5.2\\Gameplay\\Combat.md",
      "preview": "## Other Activity on Your Turn\n\nYour turn can include a variety of flourishes that require neither your action nor your move.\n\nYou can communicate however you are able, through brief utterances and ge"
    },
    {
      "rank": 8,
      "score": 0.014925373134328358,
      "category": "Characterizations",
      "topic": "Multiclassing",
      "file": "E:\\Programms\\JetBrains\\_Projects\\Python\\SeminarRAG\\src\\..\\data\\DND.SRD.Wiki-0.5.2\\Characterizations\\Multiclassing.md",
      "preview": "If you have more than one spellcasting class, this table might give you spell slots of a level that is higher than the spells you know or can prepare. You can use those slots, but only to cast your lo"
    },
    {
      "rank": 9,
      "score": 0.014705882352941176,
      "category": "Gameplay",
      "topic": "Combat",
      "file": "E:\\Programms\\JetBrains\\_Projects\\Python\\SeminarRAG\\src\\..\\data\\DND.SRD.Wiki-0.5.2\\Gameplay\\Combat.md",
      "preview": "## Bonus Actions\n\nVarious class features, spells, and other abilities let you take an additional action on your turn called a bonus action. The Cunning Action feature, for example, allows a rogue to t"
    },
    {
      "rank": 10,
      "score": 0.014492753623188406,
      "category": "Characterizations",
      "topic": "Multiclassing",
      "file": "E:\\Programms\\JetBrains\\_Projects\\Python\\SeminarRAG\\src\\..\\data\\DND.SRD.Wiki-0.5.2\\Characterizations\\Multiclassing.md",
      "preview": "## Extra Attack\n\nIf you gain the Extra Attack class feature from more than one class, the features don't add together. You can't make more than two attacks with this feature unless it says you do (as "
    }
  ],
  "tokens": {
    "rag_prompt": 2839,
    "rag_completion": 3157,
    "meta_prompt": 0,
    "meta_completion": 0,
    "total_calls": 1,
    "total": 5996
  },
  "costs": {
    "rag": 0.00091212,
    "meta": 0.0,
    "embed": 0.0,
    "total": 0.00091212
  },
  "timings": {
    "rag_s": 0.0,
    "query_s": 6.11,
    "total_s": 16.63
  },
  "answer": " No, according to the provided rules, you cannot cast a spell and make a weapon attack in the same turn without any special features. The rules state that you can only take one action at a time during your turn, and casting a spell is considered an action. Therefore, you cannot perform two actions, such as casting a spell and making a weapon attack, in the same turn without some ability or feature that allows you to do so.",
  "refused": false,
  "confidence": {
    "passed": false,
    "best_score": 0.016666666666666666
  },
  "evaluation": {
    "faithfulness": {
      "score": 1.0,
      "passing": true,
      "feedback": "YES"
    },
    "relevancy": {
      "score": 0.0,
      "passing": false,
      "feedback": "NO"
    },
    "correctness": {
      "score": 5.0,
      "passing": true,
      "feedback": "The generated answer is fully correct and directly addresses the user query, explaining the rules clearly and concisely. It accurately reflects the information in the reference answer without any mistakes."
    },
    "context_relevancy": {
      "score": 0.5,
      "passing": null,
      "feedback": "1. **Does the retrieved context match the subject matter of the user's query?**\n   - The retrieved context discusses various aspects of spellcasting and making attacks in D&D 5e, including the rules for casting spells as bonus actions, the structure of making an attack, and the limitations on casting spells in the same turn. This is relevant to the user's query about whether a spell can be cast and a weapon attack made in the same turn without special features. However, it does not explicitly answer the query regarding the possibility of doing both actions in the same turn without special features. Therefore, while the context is related, it does not directly address the specific question.\n\n   **Score: 1 point** (for partial relevance)\n\n2. **Can the retrieved context be used exclusively to provide a full answer to the user's query?**\n   - The context provides information about the mechanics of casting spells and making attacks, but it does not provide a definitive answer to the user's question. The relevant rule is that you cannot cast another spell during the same turn, except for a cantrip with a casting time of 1 action, which implies that if you cast a spell (not a cantrip) using your action, you cannot make a weapon attack with your action. However, if you cast a spell as a bonus action, you can still make a weapon attack as your action. The context does not clarify this distinction clearly enough to provide a full answer to the user's query.\n\n   **Score: 1 point** (for partial usefulness)\n\n**Final Result: [RESULT] 2.0**"
    }
  }
}