{
  "query_id": "query_003",
  "session_id": "32-retrieval-fusion-3q-Overnight-30q-v1-20260315-133132",
  "timestamp": "2026-03-15T13:32:09.714367",
  "query": {
    "original": "What damage type does Inflict Wounds deal?",
    "used": "What damage type does Inflict Wounds deal?"
  },
  "retrieved_nodes": [
    {
      "rank": 1,
      "score": 0.05,
      "category": "Spells",
      "topic": "Inflict Wounds",
      "file": "E:\\Programms\\JetBrains\\_Projects\\Python\\SeminarRAG\\src\\..\\data\\DND.SRD.Wiki-0.5.2\\Spells\\Inflict Wounds.md",
      "preview": "### Inflict Wounds\n\n*1st-level necromancy*\n\n**Casting Time:** 1 action\n\n**Range:** Touch\n\n**Components:** V, S\n\n**Duration:** Instantaneous\n\nMake a melee spell attack against a creature you can reach."
    },
    {
      "rank": 2,
      "score": 0.048651507139079855,
      "category": "Treasure",
      "topic": "Sword of Wounding",
      "file": "E:\\Programms\\JetBrains\\_Projects\\Python\\SeminarRAG\\src\\..\\data\\DND.SRD.Wiki-0.5.2\\Treasure\\Sword of Wounding.md",
      "preview": "### Sword of Wounding\n\n*Weapon (any sword), rare (requires attunement)*\n\nHit points lost to this weapon's damage can be regained only through a short or long rest, rather than by regeneration, magic, "
    },
    {
      "rank": 3,
      "score": 0.048171500630517027,
      "category": "Gameplay",
      "topic": "Combat",
      "file": "E:\\Programms\\JetBrains\\_Projects\\Python\\SeminarRAG\\src\\..\\data\\DND.SRD.Wiki-0.5.2\\Gameplay\\Combat.md",
      "preview": "### Damage Types\n\nDifferent attacks, damaging spells, and other harmful effects deal different types of damage. Damage types have no rules of their own, but other rules, such as damage resistance, rel"
    },
    {
      "rank": 4,
      "score": 0.04642338900734423,
      "category": "Spells",
      "topic": "Cure Wounds",
      "file": "E:\\Programms\\JetBrains\\_Projects\\Python\\SeminarRAG\\src\\..\\data\\DND.SRD.Wiki-0.5.2\\Spells\\Cure Wounds.md",
      "preview": "### Cure Wounds\n\n*1st-level evocation*\n\n**Casting Time:** 1 action\n\n**Range:** Touch\n\n**Components:** V, S\n\n**Duration:** Instantaneous\n\nA creature you touch regains a number of hit points equal to 1d"
    },
    {
      "rank": 5,
      "score": 0.03125,
      "category": "Gameplay",
      "topic": "Combat",
      "file": "E:\\Programms\\JetBrains\\_Projects\\Python\\SeminarRAG\\src\\..\\data\\DND.SRD.Wiki-0.5.2\\Gameplay\\Combat.md",
      "preview": "### Damage Resistance and Vulnerability\n\nSome creatures and objects are exceedingly difficult or unusually easy to hurt with certain types of damage.\n\nIf a creature or an object has **resistance** to "
    },
    {
      "rank": 6,
      "score": 0.030798389007344232,
      "category": "Treasure",
      "topic": "Periapt of Wound Closure",
      "file": "E:\\Programms\\JetBrains\\_Projects\\Python\\SeminarRAG\\src\\..\\data\\DND.SRD.Wiki-0.5.2\\Treasure\\Periapt of Wound Closure.md",
      "preview": "### Periapt of Wound Closure\n\n*Wondrous item, uncommon (requires attunement)*\n\nWhile you wear this pendant, you stabilize whenever you are dying at the start of your turn. In addition, whenever you ro"
    },
    {
      "rank": 7,
      "score": 0.03057889822595705,
      "category": "Gameplay",
      "topic": "Combat",
      "file": "E:\\Programms\\JetBrains\\_Projects\\Python\\SeminarRAG\\src\\..\\data\\DND.SRD.Wiki-0.5.2\\Gameplay\\Combat.md",
      "preview": "### Damage Rolls\n\nEach weapon, spell, and harmful monster ability specifies the damage it deals. You roll the damage die or dice, add any modifiers, and apply the damage to your target. Magic weapons,"
    },
    {
      "rank": 8,
      "score": 0.028985507246376812,
      "category": "Treasure",
      "topic": "Armor of Vulnerability",
      "file": "E:\\Programms\\JetBrains\\_Projects\\Python\\SeminarRAG\\src\\..\\data\\DND.SRD.Wiki-0.5.2\\Treasure\\Armor of Vulnerability.md",
      "preview": "### Armor of Vulnerability\n\n*Armor (plate), rare (requires attunement)*\n\nWhile wearing this armor, you have resistance to one of the following damage types: bludgeoning, piercing, or slashing. The GM "
    },
    {
      "rank": 9,
      "score": 0.016129032258064516,
      "category": "Monsters",
      "topic": "Imp (Devil)",
      "file": "E:\\Programms\\JetBrains\\_Projects\\Python\\SeminarRAG\\src\\..\\data\\DND.SRD.Wiki-0.5.2\\Monsters\\Imp (Devil).md",
      "preview": "###### Actions\n\n***Sting (Bite in Beast Form)***. *Melee Weapon Attack:* +5 to hit, reach 5 ft., one target. *Hit:* 5 (1d4+3) piercing damage, and the target must make on a DC 11 Constitution saving t"
    },
    {
      "rank": 10,
      "score": 0.015384615384615385,
      "category": "Gamemastering",
      "topic": "Objects",
      "file": "E:\\Programms\\JetBrains\\_Projects\\Python\\SeminarRAG\\src\\..\\data\\DND.SRD.Wiki-0.5.2\\Gamemastering\\Objects.md",
      "preview": "## Statistics for Objects\n\nWhen time is a factor, you can assign an Armor Class and hit points to a destructible object. You can also give it immunities, resistances, and vulnerabilities to specific t"
    }
  ],
  "tokens": {
    "rag_prompt": 3428,
    "rag_completion": 3701,
    "meta_prompt": 0,
    "meta_completion": 0,
    "total_calls": 2,
    "total": 7129
  },
  "costs": {
    "rag": 0.00108027,
    "meta": 0.0,
    "embed": 0.0,
    "total": 0.00108027
  },
  "timings": {
    "rag_s": 0.0,
    "query_s": 4.77,
    "total_s": 11.64
  },
  "answer": " Inflict Wounds deals necrotic damage.",
  "refused": false,
  "confidence": {
    "passed": false,
    "best_score": 0.05
  },
  "evaluation": {
    "faithfulness": {
      "score": 1.0,
      "passing": true,
      "feedback": "YES"
    },
    "relevancy": {
      "score": 1.0,
      "passing": true,
      "feedback": "YES"
    },
    "correctness": {
      "score": 5.0,
      "passing": true,
      "feedback": "The generated answer is fully correct and matches the reference answer exactly, providing the precise information requested by the user."
    },
    "context_relevancy": {
      "score": 1.0,
      "passing": null,
      "feedback": "1. **Does the retrieved context match the subject matter of the user's query?**\n   - Yes, the retrieved context directly addresses the query about the damage type of the spell \"Inflict Wounds.\" It specifies that the spell deals \"3d10 necrotic damage,\" which is the exact information requested.\n\n2. **Can the retrieved context be used exclusively to provide a full answer to the user's query?**\n   - Yes, the context provides a complete answer to the query. It clearly states the damage type (necrotic) associated with the spell \"Inflict Wounds\" without needing additional information from other sources.\n\n**Feedback:**\nThe retrieved context is highly relevant and directly answers the user's question about the damage type of \"Inflict Wounds.\" It provides specific details about the spell, including its casting time, range, and the damage it inflicts, which is all pertinent to understanding the spell's effects. There are no extraneous details that detract from the answer, making it concise and informative.\n\nFinal result: [RESULT] 4.0"
    }
  }
}